[
  {
    "color|1": ["green-btn",   "tiffany-btn", "yellow-btn"],
    "title|1": "@sentence(1)"
  },
    {
    "color|1": ["green-btn",   "tiffany-btn", "yellow-btn"],
    "title|1": "@sentence(1)"
  },
    {
    "color|1": ["green-btn",   "tiffany-btn", "yellow-btn"],
    "title|1": "@sentence(1)"
  },
    {
    "color|1": ["green-btn",   "tiffany-btn", "yellow-btn"],
    "title|1": "@sentence(1)"
  },
    {
    "color|1": ["green-btn",   "tiffany-btn", "yellow-btn"],
    "title|1": "@sentence(1)"
  },
    {
    "color|1": ["green-btn",   "tiffany-btn", "yellow-btn"],
    "title|1": "@sentence(1)"
  }
]